{
    "list": [
        {
            "prefabName": "PrefabItem_Book",
            "displayName": "Item: Book",
            "size": {
                "x": 64.0,
                "y": 64.0
            }
        },
        {
            "prefabName": "PrefabItem_Box",
            "displayName": "Item: Box",
            "size": {
                "x": 64.0,
                "y": 64.0
            }
        },
        {
            "prefabName": "PrefabItem_Burger",
            "displayName": "Item: Hamburger",
            "size": {
                "x": 64.0,
                "y": 64.0
            }
        },
        {
            "prefabName": "PrefabItem_Cross",
            "displayName": "Item: Crucifix",
            "size": {
                "x": 64.0,
                "y": 64.0
            }
        },
        {
            "prefabName": "PrefabItem_Mushroom",
            "displayName": "Item: Mushroom",
            "size": {
                "x": 64.0,
                "y": 64.0
            }
        },
        {
            "prefabName": "PrefabItem_Phone",
            "displayName": "Item: Cellphone",
            "size": {
                "x": 64.0,
                "y": 64.0
            }
        },
        {
            "prefabName": "PrefabItem_Duck",
            "displayName": "Item: Rubber Ducky",
            "size": {
                "x": 64.0,
                "y": 64.0
            }
        },
        {
            "prefabName": "PrefabItem_ToiPa",
            "displayName": "Item: Toilet Paper",
            "size": {
                "x": 64.0,
                "y": 64.0
            }
        }
    ]
}