{
    "list": [
        {
            "prefabName": "PrefabRoom_Generic",
            "displayName": "Generic",
            "size": {
                "x": 9.6,
                "y": 4.8
            },
            "maxInstances": 99,
            "doorSpawnLeft": true,
            "doorSpawnRight": true,
            "doorSpawns": [
                -2.0,
				2.0
            ],
            "itemSpawns": [
                {
                    "x": -3.6,
                    "y": -1.4
                },
                {
                    "x": 0.0,
                    "y": -0.2
                },
                {
                    "x": 3.6,
                    "y": -1.4
                }
            ]
        },
        {
            "prefabName": "PrefabRoom_Hallway",
            "displayName": "Generic Hallway",
            "size": {
                "x": 28.8,
                "y": 4.8
            },
            "maxInstances": 99,
            "doorSpawnLeft": true,
            "doorSpawnRight": true,
            "doorSpawns": [
                -9.6,
				-4.8,
				0.0,
				4.8,
				9.6
            ],
            "itemSpawns": [ ]
        },
        {
            "prefabName": "PrefabRoom_Foyer",
            "displayName": "Foyer",
            "size": {
                "x": 7.78,
                "y": 4.8
            },
            "maxInstances": 1,
            "doorSpawnLeft": true,
            "doorSpawnRight": false,
            "doorSpawns": [
                -0.4
            ],
            "itemSpawns": [
                {
                    "x": -2.2,
                    "y": -1.2
                },
                {
                    "x": 1.2,
                    "y": -1.2
                },
                {
                    "x": 2.8,
                    "y": -0.8
                }
            ]
        }
    ]
}